{
  "title": "KSM SDK: Python (Comprehensive)",
  "description": "A comprehensive guide to the Keeper Secrets Manager Python SDK. Covers setup, auth (token, file, Base64 config), caching, record lifecycle (create, retrieve, update, delete), password generation, file operations (upload, download, delete), and folder management (create, list, update, delete).",
  "details": {
    "steps": [
      {
        "title": "Step 1: Connection & Configuration (File, In-Memory)",
        "text": "step1.md"
      },
      {
        "title": "Step 2: Specific Secret Retrieval & Caching",
        "text": "step2.md"
      },
      {
        "title": "Step 3: Creating Records & Password Generation",
        "text": "step3.md"
      },
      {
        "title": "Step 4: Record Updates & File Management",
        "text": "step4-fileupload.md"
      },
      {
        "title": "Step 5: Folder Management & Record Deletion (with Caching)",
        "text": "step5-inmemorystorage.md"
      }
    ],
    "intro": {
      "text": "intro.md",
      "code": "install-ksm-sdk.sh"
    },
    "finish": {
      "text": "finish.md"
    }
  },
  "environment": {
    "hideintro": false, 
    "hidefinish": false, 
    "uilayout": "editor-terminal"
  },
  "backend": {
    "imageid": "ubuntu"
  },
  "interface": {
    "layout": "ide"
  }
}