{
  "pathwayTitle": "Docker",
  "title": "KSM Integration: Docker",
  "description": "Learn how to user KSM in Docker",
  "difficulty": "intermediate",
  "details": {
    "steps": [
      {
        "title": "Step 1: Pre-requisites",
        "text": "step1.md"
      },
      {
        "title": "Step 2: Start DB Service",
        "text": "step2.md"
      },
      {
        "title": "Step 3: Connect to DB",
        "text": "step3.md"
      }
    ],
    "intro": {
      "text": "intro.md"
    },
    "finish": {
      "text": "finish.md"
    }
  },
  "environment": {
    "uieditorpath": "/root/workdir",
    "uilayout": "editor-terminal",
    "uimessage1": "\u001b[32mYour Interactive Bash Terminal.\u001b[m\r\n",
    "hideintro": true,
    "hidefinish": true
  },
  "backend": {
    "imageid": "python"
  }
}